labfile/__init__.py
labfile/config.py
labfile/labfile.lark
labfile/model/__init__.py
labfile/model/tree.py
labfile/parse/__init__.py
labfile/parse/parser.py
labfile/parse/transform.py
labfile-0.0.1.dist-info/METADATA
labfile-0.0.1.dist-info/WHEEL
labfile-0.0.1.dist-info/licenses/LICENSE
labfile-0.0.1.dist-info/RECORD
