Metadata-Version: 2.4
Name: labfile
Version: 0.0.1
Summary: A declarative file format for scientific experiments.
Project-URL: Homepage, https://github.com/flywhl/labfile
Project-URL: Repository, https://github.com/flywhl/labfile
Project-URL: Documentation, https://github.com/flywhl/labfile#readme
Project-URL: Bug Tracker, https://github.com/flywhl/labfile/issues
Author-email: Rory Byrne <rory@rory.bio>
License-Expression: MIT
License-File: LICENSE
Classifier: Development Status :: 3 - Alpha
Classifier: Intended Audience :: Developers
Classifier: Intended Audience :: Information Technology
Classifier: License :: OSI Approved :: Apache Software License
Classifier: Operating System :: OS Independent
Classifier: Programming Language :: Python
Classifier: Programming Language :: Python :: 3
Classifier: Programming Language :: Python :: 3.8
Classifier: Programming Language :: Python :: 3.9
Classifier: Programming Language :: Python :: 3.10
Classifier: Programming Language :: Python :: 3.11
Classifier: Programming Language :: Python :: 3.12
Classifier: Topic :: Scientific/Engineering
Classifier: Topic :: Software Development :: Libraries :: Python Modules
Classifier: Typing :: Typed
Requires-Python: >=3.8
Requires-Dist: lark>=1.2.2
Requires-Dist: pydantic-settings>=2.6.1
Requires-Dist: pydantic>=2.10.3
